zenoss_client.py
python_zenoss_client-1.0.1.dist-info/LICENSE
python_zenoss_client-1.0.1.dist-info/METADATA
python_zenoss_client-1.0.1.dist-info/WHEEL
python_zenoss_client-1.0.1.dist-info/top_level.txt
python_zenoss_client-1.0.1.dist-info/RECORD
