Metadata-Version: 2.1
Name: python-zenoss-client
Version: 1.0.1
Summary: Zenoss API client for python
Home-page: https://github.com/sayanarijit/python-zenoss-client
Author: Arijit Basu
Author-email: sayanarijit@gmail.com
License: MIT
Download-URL: https://github.com/sayanarijit/python-zenoss-client/archive/v1.0.1.tar.gz
Keywords: zenoss json api client
Platform: UNKNOWN
Classifier: Development Status :: 5 - Production/Stable
Classifier: Intended Audience :: Developers
Classifier: Intended Audience :: Information Technology
Classifier: Intended Audience :: System Administrators
Classifier: License :: OSI Approved :: MIT License
Classifier: Natural Language :: English
Classifier: Programming Language :: Python :: 2
Classifier: Programming Language :: Python :: 2.6
Classifier: Programming Language :: Python :: 2.7
Classifier: Programming Language :: Python :: 3
Classifier: Programming Language :: Python :: 3.2
Classifier: Programming Language :: Python :: 3.3
Classifier: Programming Language :: Python :: 3.4
Classifier: Programming Language :: Python :: 3.5
Classifier: Programming Language :: Python :: 3.6
Classifier: Topic :: Utilities
Classifier: Operating System :: MacOS
Classifier: Operating System :: POSIX
Requires-Dist: requests (==2.20.0)
